codebots/__init__.py
codebots/client_secrets.json
codebots/settings.json
codebots/bots/__init__.py
codebots/bots/_bot.py
codebots/bots/deploybot.py
codebots/bots/drivebot.py
codebots/bots/emailbot.py
codebots/bots/latexbot.py
codebots/bots/slackbot.py
codebots/bots/sshbot.py
codebots/bots/telebot.py
codebots/cli/__init__.py
codebots/cli/cli.py
codebots/decorators/__init__.py
codebots/decorators/decorators.py
codebots/utilities/__init__.py
codebots/utilities/deploy.py
codebots/utilities/message.py
codebots/utilities/os_tools.py
codebots/utilities/ssh.py
codebots/utilities/tokens.py
codebots/utilities/web_tools.py
codebots-0.11.1.dist-info/AUTHORS.rst
codebots-0.11.1.dist-info/LICENSE
codebots-0.11.1.dist-info/METADATA
codebots-0.11.1.dist-info/WHEEL
codebots-0.11.1.dist-info/entry_points.txt
codebots-0.11.1.dist-info/top_level.txt
codebots-0.11.1.dist-info/RECORD
