Metadata-Version: 2.1
Name: codebots
Version: 0.11.1
Summary: collection of bots for tasks automation
Home-page: https://github.com/franaudo/codebots
Author: Francesco Ranaudo
Author-email: ranaudo@arch.ethz.ch
License: MIT license
Keywords: codebots
Platform: UNKNOWN
Classifier: Development Status :: 2 - Pre-Alpha
Classifier: Intended Audience :: Developers
Classifier: License :: OSI Approved :: MIT License
Classifier: Natural Language :: English
Classifier: Programming Language :: Python :: 3
Classifier: Programming Language :: Python :: 3.5
Classifier: Programming Language :: Python :: 3.6
Classifier: Programming Language :: Python :: 3.7
Classifier: Programming Language :: Python :: 3.8
Requires-Python: >=3.5
License-File: LICENSE
License-File: AUTHORS.rst
Requires-Dist: Click (>=7.0)
Requires-Dist: slack-sdk
Requires-Dist: yagmail
Requires-Dist: gitpython
Requires-Dist: paramiko
Requires-Dist: pydrive
